{
  "ProviderId": "Microsoft.VisualStudio.ConnectedService.Wcf",
  "Version": "15.0.40203.910",
  "GettingStartedDocument": {
    "Uri": "https://go.microsoft.com/fwlink/?linkid=858517"
  },
  "ExtendedData": {
    "inputs": [
      "http://10.1.1.86/WebServices/Api/SalesApi.asmx"
    ],
    "collectionTypes": [
      "System.Array",
      "System.Collections.Generic.Dictionary`2"
    ],
    "namespaceMappings": [
      "*, SalesApi"
    ],
    "references": [
      "Microsoft.AspNetCore.Cors, {Microsoft.AspNetCore.Cors, 2.2.0}",
      "Microsoft.AspNetCore.Http.Abstractions, {Microsoft.AspNetCore.Http.Abstractions, 2.2.0}",
      "Microsoft.AspNetCore.Http.Extensions, {Microsoft.AspNetCore.Http.Extensions, 2.2.0}",
      "Microsoft.AspNetCore.Http.Features, {Microsoft.AspNetCore.Http.Features, 2.2.0}",
      "Microsoft.Extensions.Configuration.Abstractions, {Microsoft.Extensions.Configuration.Abstractions, 2.2.0}",
      "Microsoft.Extensions.DependencyInjection.Abstractions, {Microsoft.Extensions.DependencyInjection.Abstractions, 2.2.0}",
      "Microsoft.Extensions.FileProviders.Abstractions, {Microsoft.Extensions.FileProviders.Abstractions, 2.2.0}",
      "Microsoft.Extensions.Logging.Abstractions, {Microsoft.Extensions.Logging.Abstractions, 2.2.0}",
      "Microsoft.Extensions.Options, {Microsoft.Extensions.Options, 2.2.0}",
      "Microsoft.Extensions.Primitives, {Microsoft.Extensions.Primitives, 2.2.0}",
      "Microsoft.Net.Http.Headers, {Microsoft.Net.Http.Headers, 2.2.0}",
      "Newtonsoft.Json, {Newtonsoft.Json, 12.0.3}",
      "System.Runtime.CompilerServices.Unsafe, {System.Runtime.CompilerServices.Unsafe, 4.5.1}",
      "System.ServiceModel, {System.ServiceModel.Primitives, 4.4.4}",
      "System.ServiceModel.Duplex, {System.ServiceModel.Duplex, 4.4.4}",
      "System.ServiceModel.Http, {System.ServiceModel.Http, 4.4.4}",
      "System.ServiceModel.NetTcp, {System.ServiceModel.NetTcp, 4.4.4}",
      "System.ServiceModel.Primitives, {System.ServiceModel.Primitives, 4.4.4}",
      "System.ServiceModel.Security, {System.ServiceModel.Security, 4.4.4}",
      "System.Text.Encodings.Web, {System.Text.Encodings.Web, 4.5.0}"
    ],
    "targetFramework": "netcoreapp3.1",
    "typeReuseMode": "All"
  }
}